examples/app_test/__init__.py
examples/app_test/app.py
examples/arabic/__init__.py
examples/danish/__init__.py
examples/danish/danish_zero_shot_experiment.py
examples/english/__init__.py
examples/english/english_experiment.py
examples/english/english_experiment_multiple_folds.py
examples/english/transformer_configs.py
examples/greek/__init__.py
examples/greek/greek_zero_shot_experiment.py
examples/olid/__init__.py
examples/olid/olid_zero_shot_experiment.py
hatespans/__init__.py
hatespans/algo/__init__.py
hatespans/algo/evaluation.py
hatespans/algo/hate_spans_model.py
hatespans/algo/language_modeling.py
hatespans/algo/language_modeling_utils.py
hatespans/algo/predict.py
hatespans/algo/preprocess.py
hatespans/algo/utils.py
hatespans/algo/custom_models/__init__.py
hatespans/algo/custom_models/models.py
hatespans/app/__init__.py
hatespans/app/hate_spans_app.py
hatespans/config/__init__.py
hatespans/config/global_args.py
hatespans/config/model_args.py
hatespans/config/utils.py
hatespans-0.2.0.dist-info/LICENSE
hatespans-0.2.0.dist-info/METADATA
hatespans-0.2.0.dist-info/WHEEL
hatespans-0.2.0.dist-info/top_level.txt
hatespans-0.2.0.dist-info/RECORD
