Metadata-Version: 2.1
Name: hatespans
Version: 0.2.0
Summary: Toxic Spans Prediction
Home-page: https://github.com/TharinduDR/HateSpans
Author: Tharindu Ranasinghe
Author-email: rhtdranasinghe@gmail.com
License: UNKNOWN
Platform: UNKNOWN
Classifier: Intended Audience :: Science/Research
Classifier: License :: OSI Approved :: Apache Software License
Classifier: Programming Language :: Python :: 3
Classifier: Topic :: Scientific/Engineering :: Artificial Intelligence
Requires-Python: >=3.6
Requires-Dist: spacy (==2.3.4)
Requires-Dist: pandas (==1.1.4)
Requires-Dist: transformers (==3.5.1)
Requires-Dist: seqeval (==1.2.2)
Requires-Dist: tensorboardX (==2.1)
Requires-Dist: wandb (==0.10.11)
Requires-Dist: googledrivedownloader (==0.4)
